argos_netbox-0.1.3.dist-info/METADATA
argos_netbox-0.1.3.dist-info/WHEEL
argos_netbox/README.md
argos_netbox/__init__.py
argos_netbox/api/__init__.py
argos_netbox/api/serializers.py
argos_netbox/api/urls.py
argos_netbox/api/views.py
argos_netbox/filtersets.py
argos_netbox/forms.py
argos_netbox/graphql.py
argos_netbox/migrations/.mypy_cache/.gitignore
argos_netbox/migrations/.mypy_cache/3.11/@plugins_snapshot.json
argos_netbox/migrations/.mypy_cache/3.11/_ast.data.json
argos_netbox/migrations/.mypy_cache/3.11/_ast.meta.json
argos_netbox/migrations/.mypy_cache/3.11/_codecs.data.json
argos_netbox/migrations/.mypy_cache/3.11/_codecs.meta.json
argos_netbox/migrations/.mypy_cache/3.11/_collections_abc.data.json
argos_netbox/migrations/.mypy_cache/3.11/_collections_abc.meta.json
argos_netbox/migrations/.mypy_cache/3.11/_ctypes.data.json
argos_netbox/migrations/.mypy_cache/3.11/_ctypes.meta.json
argos_netbox/migrations/.mypy_cache/3.11/_typeshed/__init__.data.json
argos_netbox/migrations/.mypy_cache/3.11/_typeshed/__init__.meta.json
argos_netbox/migrations/.mypy_cache/3.11/_winapi.data.json
argos_netbox/migrations/.mypy_cache/3.11/_winapi.meta.json
argos_netbox/migrations/.mypy_cache/3.11/abc.data.json
argos_netbox/migrations/.mypy_cache/3.11/abc.meta.json
argos_netbox/migrations/.mypy_cache/3.11/array.data.json
argos_netbox/migrations/.mypy_cache/3.11/array.meta.json
argos_netbox/migrations/.mypy_cache/3.11/builtins.data.json
argos_netbox/migrations/.mypy_cache/3.11/builtins.meta.json
argos_netbox/migrations/.mypy_cache/3.11/codecs.data.json
argos_netbox/migrations/.mypy_cache/3.11/codecs.meta.json
argos_netbox/migrations/.mypy_cache/3.11/collections/__init__.data.json
argos_netbox/migrations/.mypy_cache/3.11/collections/__init__.meta.json
argos_netbox/migrations/.mypy_cache/3.11/collections/abc.data.json
argos_netbox/migrations/.mypy_cache/3.11/collections/abc.meta.json
argos_netbox/migrations/.mypy_cache/3.11/contextlib.data.json
argos_netbox/migrations/.mypy_cache/3.11/contextlib.meta.json
argos_netbox-0.1.3.dist-info/RECORD
