Metadata-Version: 2.1
Name: argos-netbox
Version: 0.1.3
Author-Email: Dominic Walther <dominic.walther@ost.ch>, Dejan Jovicic <dejan.jovicic@ost.ch>
Classifier: Development Status :: 4 - Beta
Classifier: Intended Audience :: Developers
Classifier: Operating System :: OS Independent
Project-URL: Repository, https://gitlab.ost.ch/pydantic-sa/netboxify
Requires-Python: >=3.9
